injector/app.py
hana_injector-0.0.1.dist-info/LICENSE
hana_injector-0.0.1.dist-info/METADATA
hana_injector-0.0.1.dist-info/WHEEL
hana_injector-0.0.1.dist-info/entry_points.txt
hana_injector-0.0.1.dist-info/top_level.txt
hana_injector-0.0.1.dist-info/RECORD
