Metadata-Version: 2.1
Name: hana-injector
Version: 0.0.1
Summary: An MQTT stream to SAP HANA database injector
Home-page: https://github.com/ZPascal/hana-injector
Author: Pascal Zimmermann
Author-email: info@theiotstudio.com
Project-URL: Source, https://github.com/ZPascal/hana-injector
Project-URL: Bug Tracker, https://github.com/ZPascal/hana-injector/issues
Project-URL: Documentation, https://zpascal.github.io/hana-injector/
Classifier: Programming Language :: Python :: 3
Classifier: License :: OSI Approved
Classifier: Operating System :: OS Independent
Requires-Python: >=3.6
License-File: LICENSE
Requires-Dist: appdirs (==1.4.4)
Requires-Dist: bcrypt (==4.0.1)
Requires-Dist: black (==22.10.0)
Requires-Dist: cffi (==1.15.1)
Requires-Dist: click (==8.1.3)
Requires-Dist: distro (==1.8.0)
Requires-Dist: Flask (==2.2.2)
Requires-Dist: Flask-Bcrypt (==1.0.1)
Requires-Dist: flask-prometheus-metrics (==1.0.0)
Requires-Dist: Flask-WTF (==1.0.1)
Requires-Dist: itsdangerous (==2.1.2)
Requires-Dist: Jinja2 (==3.1.2)
Requires-Dist: jsonformatter (==0.3.2)
Requires-Dist: MarkupSafe (==2.1.1)
Requires-Dist: mypy-extensions (==0.4.3)
Requires-Dist: paho-mqtt (==1.6.1)
Requires-Dist: pathspec (==0.10.1)
Requires-Dist: platformdirs (==2.5.2)
Requires-Dist: prometheus-client (==0.15.0)
Requires-Dist: pycparser (==2.21)
Requires-Dist: pyhdb (==0.3.4)
Requires-Dist: regex (==2022.10.31)
Requires-Dist: ruamel.yaml (==0.17.21)
Requires-Dist: ruamel.yaml.clib (==0.2.7)
Requires-Dist: six (==1.16.0)
Requires-Dist: toml (==0.10.2)
Requires-Dist: tomli (==2.0.1)
Requires-Dist: typed-ast (==1.5.4)
Requires-Dist: typing-extensions (==4.4.0)
Requires-Dist: waitress (==2.1.2)
Requires-Dist: Werkzeug (==2.2.2)
